discord_notifier_bot/__init__.py
discord_notifier_bot/__main__.py
discord_notifier_bot/bot.py
discord_notifier_bot/cli.py
discord_notifier_bot-0.3.3.dist-info/LICENSE
discord_notifier_bot-0.3.3.dist-info/METADATA
discord_notifier_bot-0.3.3.dist-info/WHEEL
discord_notifier_bot-0.3.3.dist-info/entry_points.txt
discord_notifier_bot-0.3.3.dist-info/top_level.txt
discord_notifier_bot-0.3.3.dist-info/RECORD
