Metadata-Version: 2.1
Name: discord-notifier-bot
Version: 0.3.3
Summary: A cli bot to send simple messages to a Discord channel.
Home-page: https://github.com/Querela/discord-notifier-bot
Author: Erik Körner
Author-email: koerner@informatik.uni-leipzig.de
License: MIT License
Keywords: discord,bot,notifier,cli
Platform: UNKNOWN
Classifier: Development Status :: 4 - Beta
Classifier: Environment :: Console
Classifier: License :: OSI Approved :: MIT License
Classifier: Operating System :: POSIX
Classifier: Programming Language :: Python :: 3
Classifier: Programming Language :: Python :: 3.6
Classifier: Programming Language :: Python :: 3.7
Classifier: Programming Language :: Python :: 3.8
Classifier: Topic :: Utilities
Requires-Python: >=3.6
Requires-Dist: discord.py
